{
    "format_version": "1.10.0",
    "minecraft:block": {
        "components": {
            "minecraft:destroy_time": 30.0,
            "minecraft:explosion_resistance": {
                "value": 20.0
            },
            "netease:tier": {
                "destroy_special": true,
                "digger": "pickaxe",
                "level": 2
            }
        },
        "description": {
            "identifier": "qnute:enderOreBlock",
            "register_to_creative_menu": true
        }
    }
}